README.md
ptree.py
setup.py
ptree.egg-info/PKG-INFO
ptree.egg-info/SOURCES.txt
ptree.egg-info/dependency_links.txt
ptree.egg-info/top_level.txt