Metadata-Version: 2.1
Name: ptree
Version: 0.3
Summary: Work with PairTree file system convention
Home-page: http://github.com/edsu/ptree
Author: Ed Summers
Author-email: ehs@pobox.com
License: UNKNOWN
Platform: POSIX
Classifier: License :: Public Domain
Classifier: Intended Audience :: Developers
Classifier: Topic :: Communications :: File Sharing
Classifier: Topic :: Software Development :: Libraries :: Python Modules
Classifier: Topic :: System :: Filesystems
Classifier: Programming Language :: Python :: 2.7
Classifier: Programming Language :: Python :: 3
Classifier: Programming Language :: Python :: 3.7
